secondshot/__init__.py
secondshot/_version.py
secondshot/actions.py
secondshot/alembic.ini
secondshot/config.py
secondshot/constants.py
secondshot/main.py
secondshot/models.py
secondshot/syslogger.py
secondshot/alembic/__init.py__
secondshot/alembic/env.py
secondshot/alembic/script.py.mako
secondshot/alembic/versions/23296991a8e5_add_config_table.py
secondshot/alembic/versions/6cf114485e53_drop_manifests.py
secondshot/alembic/versions/ab8ec674d281_initialize_database.py
secondshot-0.10.5.data/scripts/check_rsnap.py
secondshot-0.10.5.data/scripts/cron-secondshot.sh
secondshot-0.10.5.data/scripts/rrsync
secondshot-0.10.5.dist-info/LICENSE.txt
secondshot-0.10.5.dist-info/METADATA
secondshot-0.10.5.dist-info/WHEEL
secondshot-0.10.5.dist-info/entry_points.txt
secondshot-0.10.5.dist-info/top_level.txt
secondshot-0.10.5.dist-info/RECORD
