Metadata-Version: 2.1
Name: secondshot
Version: 0.10.5
Summary: Linux-based backup utility
Home-page: https://github.com/instantlinux/secondshot
Author: Rich Braun
Author-email: richb@instantlinux.net
Keywords: backup rsync rsnapshot
Classifier: Development Status :: 3 - Alpha
Classifier: License :: OSI Approved :: GNU Lesser General Public License v2 or later (LGPLv2+)
Classifier: Topic :: System :: Archiving :: Backup
Classifier: Intended Audience :: System Administrators
Classifier: Programming Language :: Python :: 3
Classifier: Programming Language :: Python :: 3.8
Classifier: Programming Language :: Python :: 3.9
Classifier: Programming Language :: Python :: 3.10
Classifier: Programming Language :: Python :: 3.11
Requires-Python: >=3.8
License-File: LICENSE.txt
Requires-Dist: alembic >=1.11.2
Requires-Dist: docopt >=0.6.2
Requires-Dist: pymysql <1.0
Requires-Dist: sqlalchemy <1.4
